setup.py
random_color/__init__.py
random_color.egg-info/PKG-INFO
random_color.egg-info/SOURCES.txt
random_color.egg-info/dependency_links.txt
random_color.egg-info/not-zip-safe
random_color.egg-info/top_level.txt