Metadata-Version: 1.0
Name: random_color
Version: 0.1
Summary: Generate a random hex color
Home-page: http://github.com/ghitab/random_color
Author: Ghiță Bizău
Author-email: ghitabizau27@gmail.com
License: MIT
Platform: UNKNOWN
